[
{"movie_link": "https://imdb.com/title/tt1639426/"},
{"movie_link": "https://imdb.com/title/tt1954470/"},
{"movie_link": "https://imdb.com/title/tt0986264/"},
{"movie_link": "https://imdb.com/title/tt1327035/"},
{"movie_link": "https://imdb.com/title/tt0367110/"},
{"movie_link": "https://imdb.com/title/tt1187043/"},
{"movie_link": "https://imdb.com/title/tt2283748/"},
{"movie_link": "https://imdb.com/title/tt0405508/"},
{"movie_link": "https://imdb.com/title/tt0488414/"},
{"movie_link": "https://imdb.com/title/tt5571734/"},
{"movie_link": "https://imdb.com/title/tt4934950/"},
{"movie_link": "https://imdb.com/title/tt0871510/"},
{"movie_link": "https://imdb.com/title/tt0375611/"},
{"movie_link": "https://imdb.com/title/tt0109117/"},
{"movie_link": "https://imdb.com/title/tt5600714/"},
{"movie_link": "https://imdb.com/title/tt4430212/"},
{"movie_link": "https://imdb.com/title/tt5074352/"},
{"movie_link": "https://imdb.com/title/tt0400234/"},
{"movie_link": "https://imdb.com/title/tt0050870/"},
{"movie_link": "https://imdb.com/title/tt0085743/"},
{"movie_link": "https://imdb.com/title/tt1280558/"},
{"movie_link": "https://imdb.com/title/tt0292490/"},
{"movie_link": "https://imdb.com/title/tt2338151/"},
{"movie_link": "https://imdb.com/title/tt0050188/"},
{"movie_link": "https://imdb.com/title/tt0066763/"},
{"movie_link": "https://imdb.com/title/tt1821480/"},
{"movie_link": "https://imdb.com/title/tt2082197/"},
{"movie_link": "https://imdb.com/title/tt3614516/"},
{"movie_link": "https://imdb.com/title/tt1562872/"},
{"movie_link": "https://imdb.com/title/tt0374887/"},
{"movie_link": "https://imdb.com/title/tt3322420/"},
{"movie_link": "https://imdb.com/title/tt1261047/"},
{"movie_link": "https://imdb.com/title/tt1093370/"},
{"movie_link": "https://imdb.com/title/tt5286444/"},
{"movie_link": "https://imdb.com/title/tt2224317/"},
{"movie_link": "https://imdb.com/title/tt5713232/"},
{"movie_link": "https://imdb.com/title/tt0104561/"},
{"movie_link": "https://imdb.com/title/tt4387040/"},
{"movie_link": "https://imdb.com/title/tt5005684/"},
{"movie_link": "https://imdb.com/title/tt0073707/"},
{"movie_link": "https://imdb.com/title/tt2377938/"},
{"movie_link": "https://imdb.com/title/tt0456144/"},
{"movie_link": "https://imdb.com/title/tt3390572/"},
{"movie_link": "https://imdb.com/title/tt0373856/"},
{"movie_link": "https://imdb.com/title/tt2356180/"},
{"movie_link": "https://imdb.com/title/tt1907761/"},
{"movie_link": "https://imdb.com/title/tt0242519/"},
{"movie_link": "https://imdb.com/title/tt4635372/"},
{"movie_link": "https://imdb.com/title/tt0432047/"},
{"movie_link": "https://imdb.com/title/tt2072227/"},
{"movie_link": "https://imdb.com/title/tt4088588/"},
{"movie_link": "https://imdb.com/title/tt1926313/"},
{"movie_link": "https://imdb.com/title/tt1324059/"},
{"movie_link": "https://imdb.com/title/tt2181931/"},
{"movie_link": "https://imdb.com/title/tt2350496/"},
{"movie_link": "https://imdb.com/title/tt4169250/"},
{"movie_link": "https://imdb.com/title/tt0063404/"},
{"movie_link": "https://imdb.com/title/tt2631186/"},
{"movie_link": "https://imdb.com/title/tt1620933/"},
{"movie_link": "https://imdb.com/title/tt2181831/"},
{"movie_link": "https://imdb.com/title/tt4434004/"},
{"movie_link": "https://imdb.com/title/tt1077248/"},
{"movie_link": "https://imdb.com/title/tt0112553/"},
{"movie_link": "https://imdb.com/title/tt2213054/"},
{"movie_link": "https://imdb.com/title/tt0100095/"},
{"movie_link": "https://imdb.com/title/tt0164538/"},
{"movie_link": "https://imdb.com/title/tt1839596/"},
{"movie_link": "https://imdb.com/title/tt0382383/"},
{"movie_link": "https://imdb.com/title/tt1345777/"},
{"movie_link": "https://imdb.com/title/tt1934231/"},
{"movie_link": "https://imdb.com/title/tt0347304/"},
{"movie_link": "https://imdb.com/title/tt0800956/"},
{"movie_link": "https://imdb.com/title/tt0082314/"},
{"movie_link": "https://imdb.com/title/tt1395054/"},
{"movie_link": "https://imdb.com/title/tt1014672/"},
{"movie_link": "https://imdb.com/title/tt2980794/"},
{"movie_link": "https://imdb.com/title/tt0238936/"},
{"movie_link": "https://imdb.com/title/tt2199711/"},
{"movie_link": "https://imdb.com/title/tt0356982/"},
{"movie_link": "https://imdb.com/title/tt4900716/"},
{"movie_link": "https://imdb.com/title/tt1434447/"},
{"movie_link": "https://imdb.com/title/tt1288638/"},
{"movie_link": "https://imdb.com/title/tt0499375/"},
{"movie_link": "https://imdb.com/title/tt1532957/"},
{"movie_link": "https://imdb.com/title/tt1787988/"},
{"movie_link": "https://imdb.com/title/tt1734110/"},
{"movie_link": "https://imdb.com/title/tt2882328/"},
{"movie_link": "https://imdb.com/title/tt0995718/"},
{"movie_link": "https://imdb.com/title/tt3043252/"},
{"movie_link": "https://imdb.com/title/tt0169102/"},
{"movie_link": "https://imdb.com/title/tt1230165/"},
{"movie_link": "https://imdb.com/title/tt1433810/"},
{"movie_link": "https://imdb.com/title/tt0112870/"},
{"movie_link": "https://imdb.com/title/tt5310090/"},
{"movie_link": "https://imdb.com/title/tt0200087/"},
{"movie_link": "https://imdb.com/title/tt3848892/"},
{"movie_link": "https://imdb.com/title/tt0072860/"},
{"movie_link": "https://imdb.com/title/tt0466460/"},
{"movie_link": "https://imdb.com/title/tt0453729/"},
{"movie_link": "https://imdb.com/title/tt0079590/"},
{"movie_link": "https://imdb.com/title/tt0824316/"},
{"movie_link": "https://imdb.com/title/tt2855648/"},
{"movie_link": "https://imdb.com/title/tt0195231/"},
{"movie_link": "https://imdb.com/title/tt1266583/"},
{"movie_link": "https://imdb.com/title/tt0054098/"},
{"movie_link": "https://imdb.com/title/tt3863552/"},
{"movie_link": "https://imdb.com/title/tt0433425/"},
{"movie_link": "https://imdb.com/title/tt2176013/"},
{"movie_link": "https://imdb.com/title/tt0383975/"},
{"movie_link": "https://imdb.com/title/tt2317337/"},
{"movie_link": "https://imdb.com/title/tt0088099/"},
{"movie_link": "https://imdb.com/title/tt2359810/"},
{"movie_link": "https://imdb.com/title/tt0296574/"},
{"movie_link": "https://imdb.com/title/tt1292703/"},
{"movie_link": "https://imdb.com/title/tt0811066/"},
{"movie_link": "https://imdb.com/title/tt0454431/"},
{"movie_link": "https://imdb.com/title/tt1182937/"},
{"movie_link": "https://imdb.com/title/tt0150992/"},
{"movie_link": "https://imdb.com/title/tt0065936/"},
{"movie_link": "https://imdb.com/title/tt0845448/"},
{"movie_link": "https://imdb.com/title/tt0920464/"},
{"movie_link": "https://imdb.com/title/tt0109555/"},
{"movie_link": "https://imdb.com/title/tt1274295/"},
{"movie_link": "https://imdb.com/title/tt3447364/"},
{"movie_link": "https://imdb.com/title/tt0070947/"},
{"movie_link": "https://imdb.com/title/tt0831840/"},
{"movie_link": "https://imdb.com/title/tt3495030/"},
{"movie_link": "https://imdb.com/title/tt0069671/"},
{"movie_link": "https://imdb.com/title/tt1447508/"},
{"movie_link": "https://imdb.com/title/tt3678782/"},
{"movie_link": "https://imdb.com/title/tt0337578/"},
{"movie_link": "https://imdb.com/title/tt0220832/"},
{"movie_link": "https://imdb.com/title/tt3148502/"},
{"movie_link": "https://imdb.com/title/tt1836912/"},
{"movie_link": "https://imdb.com/title/tt0352314/"},
{"movie_link": "https://imdb.com/title/tt0323013/"},
{"movie_link": "https://imdb.com/title/tt0443708/"},
{"movie_link": "https://imdb.com/title/tt0077451/"},
{"movie_link": "https://imdb.com/title/tt0476884/"},
{"movie_link": "https://imdb.com/title/tt0102825/"},
{"movie_link": "https://imdb.com/title/tt1610452/"},
{"movie_link": "https://imdb.com/title/tt1773015/"},
{"movie_link": "https://imdb.com/title/tt0437407/"},
{"movie_link": "https://imdb.com/title/tt0098999/"},
{"movie_link": "https://imdb.com/title/tt0290326/"},
{"movie_link": "https://imdb.com/title/tt1754920/"},
{"movie_link": "https://imdb.com/title/tt0347779/"},
{"movie_link": "https://imdb.com/title/tt0190419/"},
{"movie_link": "https://imdb.com/title/tt0420332/"},
{"movie_link": "https://imdb.com/title/tt2073070/"},
{"movie_link": "https://imdb.com/title/tt1263679/"},
{"movie_link": "https://imdb.com/title/tt1397492/"},
{"movie_link": "https://imdb.com/title/tt1241195/"},
{"movie_link": "https://imdb.com/title/tt1099196/"},
{"movie_link": "https://imdb.com/title/tt0402014/"},
{"movie_link": "https://imdb.com/title/tt1916728/"},
{"movie_link": "https://imdb.com/title/tt2308773/"},
{"movie_link": "https://imdb.com/title/tt1370429/"},
{"movie_link": "https://imdb.com/title/tt0090812/"},
{"movie_link": "https://imdb.com/title/tt0293342/"},
{"movie_link": "https://imdb.com/title/tt0119239/"},
{"movie_link": "https://imdb.com/title/tt0157316/"},
{"movie_link": "https://imdb.com/title/tt0088335/"},
{"movie_link": "https://imdb.com/title/tt0071730/"},
{"movie_link": "https://imdb.com/title/tt0299108/"},
{"movie_link": "https://imdb.com/title/tt0495032/"},
{"movie_link": "https://imdb.com/title/tt0473367/"},
{"movie_link": "https://imdb.com/title/tt0106333/"},
{"movie_link": "https://imdb.com/title/tt0476527/"},
{"movie_link": "https://imdb.com/title/tt0976026/"},
{"movie_link": "https://imdb.com/title/tt0439662/"},
{"movie_link": "https://imdb.com/title/tt2100543/"},
{"movie_link": "https://imdb.com/title/tt0371735/"},
{"movie_link": "https://imdb.com/title/tt0110222/"},
{"movie_link": "https://imdb.com/title/tt0347332/"},
{"movie_link": "https://imdb.com/title/tt0459293/"},
{"movie_link": "https://imdb.com/title/tt1841542/"},
{"movie_link": "https://imdb.com/title/tt1941657/"},
{"movie_link": "https://imdb.com/title/tt1227524/"},
{"movie_link": "https://imdb.com/title/tt0819810/"},
{"movie_link": "https://imdb.com/title/tt1883121/"},
{"movie_link": "https://imdb.com/title/tt1884268/"},
{"movie_link": "https://imdb.com/title/tt0494290/"},
{"movie_link": "https://imdb.com/title/tt1809399/"},
{"movie_link": "https://imdb.com/title/tt0374271/"},
{"movie_link": "https://imdb.com/title/tt0384491/"},
{"movie_link": "https://imdb.com/title/tt1017456/"},
{"movie_link": "https://imdb.com/title/tt0119861/"},
{"movie_link": "https://imdb.com/title/tt0060742/"},
{"movie_link": "https://imdb.com/title/tt0795434/"},
{"movie_link": "https://imdb.com/title/tt1188996/"},
{"movie_link": "https://imdb.com/title/tt0093578/"},
{"movie_link": "https://imdb.com/title/tt2057441/"},
{"movie_link": "https://imdb.com/title/tt0060317/"},
{"movie_link": "https://imdb.com/title/tt0420304/"},
{"movie_link": "https://imdb.com/title/tt0451631/"},
{"movie_link": "https://imdb.com/title/tt1285241/"},
{"movie_link": "https://imdb.com/title/tt1954206/"},
{"movie_link": "https://imdb.com/title/tt0059246/"},
{"movie_link": "https://imdb.com/title/tt0079221/"},
{"movie_link": "https://imdb.com/title/tt0362696/"},
{"movie_link": "https://imdb.com/title/tt0066070/"},
{"movie_link": "https://imdb.com/title/tt1216300/"},
{"movie_link": "https://imdb.com/title/tt2122340/"},
{"movie_link": "https://imdb.com/title/tt0114234/"},
{"movie_link": "https://imdb.com/title/tt0118751/"},
{"movie_link": "https://imdb.com/title/tt0156982/"},
{"movie_link": "https://imdb.com/title/tt0374342/"},
{"movie_link": "https://imdb.com/title/tt0090575/"},
{"movie_link": "https://imdb.com/title/tt0172684/"},
{"movie_link": "https://imdb.com/title/tt0075669/"},
{"movie_link": "https://imdb.com/title/tt0449994/"},
{"movie_link": "https://imdb.com/title/tt0106655/"},
{"movie_link": "https://imdb.com/title/tt0306434/"},
{"movie_link": "https://imdb.com/title/tt0110076/"},
{"movie_link": "https://imdb.com/title/tt1664809/"},
{"movie_link": "https://imdb.com/title/tt0084630/"},
{"movie_link": "https://imdb.com/title/tt1629391/"},
{"movie_link": "https://imdb.com/title/tt0485513/"},
{"movie_link": "https://imdb.com/title/tt0106986/"},
{"movie_link": "https://imdb.com/title/tt0086597/"},
{"movie_link": "https://imdb.com/title/tt0109010/"},
{"movie_link": "https://imdb.com/title/tt1020937/"},
{"movie_link": "https://imdb.com/title/tt2327389/"},
{"movie_link": "https://imdb.com/title/tt0104605/"},
{"movie_link": "https://imdb.com/title/tt0107311/"},
{"movie_link": "https://imdb.com/title/tt0454435/"},
{"movie_link": "https://imdb.com/title/tt0330843/"},
{"movie_link": "https://imdb.com/title/tt0300160/"},
{"movie_link": "https://imdb.com/title/tt1166100/"},
{"movie_link": "https://imdb.com/title/tt0964516/"},
{"movie_link": "https://imdb.com/title/tt1291465/"},
{"movie_link": "https://imdb.com/title/tt0488381/"},
{"movie_link": "https://imdb.com/title/tt0118983/"},
{"movie_link": "https://imdb.com/title/tt0098168/"},
{"movie_link": "https://imdb.com/title/tt0378072/"},
{"movie_link": "https://imdb.com/title/tt0332766/"},
{"movie_link": "https://imdb.com/title/tt0451833/"},
{"movie_link": "https://imdb.com/title/tt0437238/"},
{"movie_link": "https://imdb.com/title/tt0104607/"},
{"movie_link": "https://imdb.com/title/tt0476805/"}
]